Workbook

Sheet 预算与实际对比
A1: 记录编号 | B1: 成本中心 | C1: 部门 | D1: 费用类别 | E1: 费用子类 | F1: 财年 | G1: 月份 | H1: 预算（元） | I1: 实际支出（元） | J1: 差异额（元） | K1: 差异率（%） | L1: 年初至今预算（元） | M1: 年初至今实际（元） | N1: 年初至今差异额（元） | O1: 年初至今差异率（%） | P1: 状态 | Q1: 备注
A2: FIN-0001 | B2: CC-001 | C2: 工程部 | D2: 人员成本 | E2: 薪资 | F2: 2025 | G2: 1月 | H2: 3025000 | I2: 3014000 | J2: =I2-H2 | K2: =IFERROR((I2-H2)/H2*100,0) | L2: 3025000 | M2: 2977832 | N2: =N2-M2 | O2: =IFERROR((N2-M2)/M2*100,0) | P2: 正常
A3: FIN-0002 | B3: CC-001 | C3: 工程部 | D3: 人员成本 | E3: 福利 | F3: 2025 | G3: 1月 | H3: 455000 | I3: 440000 | J3: =I3-H3 | K3: =IFERROR((I3-H3)/H3*100,0) | L3: 455000 | M3: 438240 | N3: =N3-M3 | O3: =IFERROR((N3-M3)/M3*100,0) | P3: 正常
A4: FIN-0003 | B4: CC-001 | C4: 工程部 | D4: 运营成本 | E4: 软件许可 | F4: 2025 | G4: 1月 | H4: 130000 | I4: 143000 | J4: =I4-H4 | K4: =IFERROR((I4-H4)/H4*100,0) | L4: 130000 | M4: 143572 | N4: =N4-M4 | O4: =IFERROR((N4-M4)/M4*100,0) | P4: 超预算
A5: FIN-0004 | B5: CC-001 | C5: 工程部 | D5: 运营成本 | E5: 云基础设施 | F5: 2025 | G5: 1月 | H5: 230000 | I5: 256000 | J5: =I5-H5 | K5: =IFERROR((I5-H5)/H5*100,0) | L5: 230000 | M5: 259072 | N5: =N5-M5 | O5: =IFERROR((N5-M5)/M5*100,0) | P5: 超预算
A6: FIN-0005 | B6: CC-002 | C6: 销售部 | D6: 人员成本 | E6: 薪资 | F6: 2025 | G6: 1月 | H6: 2235000 | I6: 2220000 | J6: =I6-H6 | K6: =IFERROR((I6-H6)/H6*100,0) | L6: 2235000 | M6: 2175600 | N6: =N6-M6 | O6: =IFERROR((N6-M6)/M6*100,0) | P6: 正常
A7: FIN-0006 | B7: CC-002 | C7: 销售部 | D7: 人员成本 | E7: 销售提成 | F7: 2025 | G7: 1月 | H7: 685000 | I7: 806000 | J7: =I7-H7 | K7: =IFERROR((I7-H7)/H7*100,0) | L7: 685000 | M7: 796328 | N7: =N7-M7 | O7: =IFERROR((N7-M7)/M7*100,0) | P7: 超预算
A8: FIN-0007 | B8: CC-002 | C8: 销售部 | D8: 市场推广 | E8: 差旅与招待 | F8: 2025 | G8: 1月 | H8: 200000 | I8: 227000 | J8: =I8-H8 | K8: =IFERROR((I8-H8)/H8*100,0) | L8: 200000 | M8: 226092 | N8: =N8-M8 | O8: =IFERROR((N8-M8)/M8*100,0) | P8: 超预算
A9: FIN-0008 | B9: CC-002 | C9: 销售部 | D9: 市场推广 | E9: 活动与会议 | F9: 2025 | G9: 1月 | H9: 108000 | I9: 102000 | J9: =I9-H9 | K9: =IFERROR((I9-H9)/H9*100,0) | L9: 108000 | M9: 102408 | N9: =N9-M9 | O9: =IFERROR((N9-M9)/M9*100,0) | P9: 低于预算
A10: FIN-0009 | B10: CC-003 | C10: 市场部 | D10: 人员成本 | E10: 薪资 | F10: 2025 | G10: 1月 | H10: 1330000 | I10: 1325000 | J10: =I10-H10 | K10: =IFERROR((I10-H10)/H10*100,0) | L10: 1330000 | M10: 1340900 | N10: =N10-M10 | O10: =IFERROR((N10-M10)/M10*100,0) | P10: 正常
A11: FIN-0010 | B11: CC-003 | C11: 市场部 | D11: 市场推广 | E11: 数字广告 | F11: 2025 | G11: 1月 | H11: 395000 | I11: 447000 | J11: =I11-H11 | K11: =IFERROR((I11-H11)/H11*100,0) | L11: 395000 | M11: 438060 | N11: =N11-M11 | O11: =IFERROR((N11-M11)/M11*100,0) | P11: 超预算
A12: FIN-0011 | B12: CC-003 | C12: 市场部 | D12: 市场推广 | E12: 内容与创意 | F12: 2025 | G12: 1月 | H12: 158000 | I12: 148000 | J12: =I12-H12 | K12: =IFERROR((I12-H12)/H12*100,0) | L12: 158000 | M12: 146224 | N12: =N12-M12 | O12: =IFERROR((N12-M12)/M12*100,0) | P12: 低于预算
A13: FIN-0012 | B13: CC-003 | C13: 市场部 | D13: 运营成本 | E13: 营销技术栈 | F13: 2025 | G13: 1月 | H13: 86000 | I13: 85000 | J13: =I13-H13 | K13: =IFERROR((I13-H13)/H13*100,0) | L13: 86000 | M13: 84660 | N13: =N13-M13 | O13: =IFERROR((N13-M13)/M13*100,0) | P13: 正常
... A44: FIN-0043 | B44: CC-010 | C44: 运营部 | D44: 运营成本 | E44: 物流与供应 | F44: 2025 | G44: 2月 | H44: 324000 | I44: 335000 | J44: =I44-H44 | K44: =IFERROR((I44-H44)/H44*100,0) | L44: 648000 | M44: 672680 | N44: =N44-M44 | O44: =IFERROR((N44-M44)/M44*100,0) | P44: 正常

Sheet 汇总分析
A1: 指标 | B1: 数值
A2: 记录总数 | B2: =COUNTA('预算与实际对比'!A2:A45)
A3: 预算合计（元） | B3: =SUM('预算与实际对比'!H2:H45)
A4: 实际支出合计（元） | B4: =SUM('预算与实际对比'!I2:I45)
A5: 差异额合计（元） | B5: =B4-B3
A6: 整体差异率（%） | B6: =IFERROR(B5/B3*100,0)
A7: 超预算条目数 | B7: =COUNTIF('预算与实际对比'!P2:P45,"超预算")
A8: 正常条目数 | B8: =COUNTIF('预算与实际对比'!P2:P45,"正常")
A9: 低于预算条目数 | B9: =COUNTIF('预算与实际对比'!P2:P45,"低于预算")
A10: 年初至今预算合计（元） | B10: =SUM('预算与实际对比'!L2:L45)
A11: 年初至今实际合计（元） | B11: =SUM('预算与实际对比'!M2:M45)
A12: 年初至今差异额合计（元） | B12: =B11-B10
