Workbook

Sheet 项目跟踪表
A1: 项目编号 | B1: 项目名称 | C1: 项目经理 | D1: 所属部门 | E1: 项目状态 | F1: 优先级 | G1: 开始日期 | H1: 截止日期 | I1: 预算（元） | J1: 实际支出（元） | K1: 预算使用率（%） | L1: 当前冲刺 | M1: 冲刺速度 | N1: 任务总数 | O1: 已完成任务 | P1: 任务完成率（%） | Q1: 风险等级 | R1: 风险描述 | S1: 资源人数 | T1: 里程碑
A2: PRJ-001 | B2: AI对话平台 | C2: 陈晓雪 | D2: 产品部 | E2: 正常推进 | F2: 高 | G2: 2025-01-06 | H2: 2025-06-30 | I2: 6120000 | J2: 3020000 | K2: =J2/I2*100 | L2: 5 | M2: 42 | N2: 120 | O2: 68 | P2: =N2/M2*100 | Q2: 低 | R2: 无关键阻塞 | S2: 8 | T2: Beta版发布 2025年5月
A3: PRJ-002 | B3: ERP迁移 | C3: 吴昊 | D3: IT部 | E3: 存在风险 | F3: 关键 | G3: 2024-11-01 | H3: 2025-08-31 | I3: 8640000 | J3: 6408000 | K3: =J3/I3*100 | L3: 7 | M3: 28 | N3: 200 | O3: 105 | P3: =N3/M3*100 | Q3: 高 | R3: 历史数据映射延迟 | S3: 12 | T3: 数据割接 2025年6月
A4: PRJ-003 | B4: 移动应用v3 | C4: 孙茜 | D4: 工程部 | E4: 正常推进 | F4: 高 | G4: 2025-02-03 | H4: 2025-07-31 | I4: 4465000 | J4: 2015000 | K4: =J4/I4*100 | L4: 4 | M4: 38 | N4: 90 | O4: 52 | P4: =N4/M4*100 | Q4: 中 | R4: iOS应用审核风险 | S4: 6 | T4: 提交App Store 2025年6月
A5: PRJ-004 | B5: 数据仓库建设 | C5: 李大伟 | D5: 数据部 | E5: 已延期 | F5: 高 | G5: 2024-12-02 | H5: 2025-09-30 | I5: 6840000 | J5: 5185000 | K5: =J5/I5*100 | L5: 8 | M5: 22 | N5: 160 | O5: 88 | P5: =N5/M5*100 | Q5: 高 | R5: 基础设施供给滞后 | S5: 10 | T5: 生产上线 2025年8月
A6: PRJ-005 | B6: 品牌焕新 | C6: 张思远 | D6: 市场部 | E6: 已完成 | F6: 中 | G6: 2025-01-13 | H6: 2025-04-30 | I6: 1295000 | J6: 1260000 | K6: =J6/I6*100 | L6: 10 | M6: 30 | N6: 60 | O6: 60 | P6: =N6/M6*100 | Q6: 低 | R6: 按时完成 | S6: 4 | T6: 发布 2025年4月
A7: PRJ-006 | B7: 安全审计 | C7: 刘峰 | D7: 安全部 | E7: 正常推进 | F7: 关键 | G7: 2025-03-03 | H7: 2025-06-30 | I7: 2305000 | J7: 1115000 | K7: =J7/I7*100 | L7: 3 | M7: 45 | N7: 80 | O7: 44 | P7: =N7/M7*100 | Q7: 中 | R7: 渗透测试发现漏洞 | S7: 5 | T7: 最终报告 2025年6月
A8: PRJ-007 | B8: HR自助服务 | C8: 王惠 | D8: 人力资源部 | E8: 正常推进 | F8: 中 | G8: 2025-02-10 | H8: 2025-08-29 | I8: 2950000 | J8: 1405000 | K8: =J8/I8*100 | L8: 4 | M8: 35 | N8: 100 | O8: 48 | P8: =N8/M8*100 | Q8: 低 | R8: 轻微范围蔓延 | S8: 7 | T8: UAT 2025年7月
A9: PRJ-008 | B9: 云成本优化 | C9: 赵宇 | D9: IT部 | E9: 已完成 | F9: 中 | G9: 2025-01-06 | H9: 2025-03-31 | I9: 1010000 | J9: 950000 | K9: =J9/I9*100 | L9: 10 | M9: 40 | N9: 50 | O9: 50 | P9: =N9/M9*100 | Q9: 低 | R9: 低于预算完成 | S9: 3 | T9: 已结项 2025年3月
A10: PRJ-009 | B10: 客户门户 | C10: 徐伊 | D10: 产品部 | E10: 存在风险 | F10: 高 | G10: 2025-03-17 | H10: 2025-09-30 | I10: 5620000 | J10: 2305000 | K10: =J10/I10*100 | L10: 3 | M10: 25 | N10: 140 | O10: 52 | P10: =N10/M10*100 | Q10: 高 | R10: 第三方API依赖风险 | S10: 9 | T10: 公测 2025年8月
A11: PRJ-010 | B11: 2025合规项目 | C11: 马杰 | D11: 法务部 | E11: 正常推进 | F11: 关键 | G11: 2025-01-13 | H11: 2025-12-31 | I11: 4035000 | J11: 1655000 | K11: =J11/I11*100 | L11: 5 | M11: 38 | N11: 180 | O11: 85 | P11: =N11/M11*100 | Q11: 中 | R11: 监管时间线风险 | S11: 8 | T11: 审计提交 2025年10月
A12: PRJ-011 | B12: 销售数据看板 | C12: 陈彤 | D12: 销售部 | E12: 已完成 | F12: 低 | G12: 2025-01-06 | H12: 2025-03-31 | I12: 685000 | J12: 655000 | K12: =J12/I12*100 | L12: 10 | M12: 32 | N12: 40 | O12: 40 | P12: =N12/M12*100 | Q12: 低 | R12: 按期交付 | S12: 3 | T12: 上线 2025年3月
A13: PRJ-012 | B13: API网关v2 | C13: 王乐 | D13: 工程部 | E13: 正常推进 | F13: 高 | G13: 2025-02-24 | H13: 2025-07-31 | I13: 3095000 | J13: 1355000 | K13: =J13/I13*100 | L13: 4 | M13: 44 | N13: 85 | O13: 44 | P13: =N13/M13*100 | Q13: 低 | R13: 性能测试待进行 | S13: 5 | T13: 负载测试 2025年6月
... A31: PRJ-030 | B31: 财务报表系统 | C31: 李大伟 | D31: 财务部 | E31: 已完成 | F31: 中 | G31: 2025-01-06 | H31: 2025-03-28 | I31: 1150000 | J31: 1140000 | K31: =J31/I31*100 | L31: 10 | M31: 35 | N31: 45 | O31: 45 | P31: =N31/M31*100 | Q31: 低 | R31: 按时交付 | S31: 3 | T31: 已结项 2025年3月

Sheet 汇总分析
A1: 指标 | B1: 数值
A2: 项目总数 | B2: =COUNTA('项目跟踪表'!A2:A32)
A3: 正常推进 | B3: =COUNTIF('项目跟踪表'!E2:E32,"正常推进")
A4: 存在风险 | B4: =COUNTIF('项目跟踪表'!E2:E32,"存在风险")
A5: 已延期 | B5: =COUNTIF('项目跟踪表'!E2:E32,"已延期")
A6: 已完成 | B6: =COUNTIF('项目跟踪表'!E2:E32,"已完成")
A7: 总预算（元） | B7: =SUM('项目跟踪表'!I2:I32)
A8: 总实际支出（元） | B8: =SUM('项目跟踪表'!J2:J32)
A9: 整体预算使用率（%） | B9: =IFERROR(B8/B7*100,0)
A10: 平均冲刺速度 | B10: =AVERAGE('项目跟踪表'!M2:M32)
A11: 平均任务完成率（%） | B11: =AVERAGE('项目跟踪表'!P2:P32)
A12: 高风险项目数 | B12: =COUNTIF('项目跟踪表'!Q2:Q32,"高")
